[
    {
        "id": "https://example.com/ids/aas/7392_2122_5042_8019",
        "submodels": [
            {
                "type": "Submodel",
                "value": "https://example.com/ids/sm/8013_2122_5042_2929"
            },
            {
                "type": "Submodel",
                "value": "https://example.com/ids/sm/2213_2122_5042_5901"
            },
            {
                "type": "Submodel",
                "value": "https://example.com/ids/sm/7313_2122_5042_6263"
            },
            {
                "type": "Submodel",
                "value": "https://example.com/ids/sm/5413_2122_5042_0568"
            },
            {
                "type": "Submodel",
                "value": "https://example.com/ids/sm/2123_2122_5042_2176"
            }
        ]
    }
]